<?xml version="1.0" encoding="UTF-8"?>
<MetaDataObject xmlns="http://v8.1c.ru/8.3/MDClasses" xmlns:app="http://v8.1c.ru/8.2/managed-application/core" xmlns:cfg="http://v8.1c.ru/8.1/data/enterprise/current-config" xmlns:cmi="http://v8.1c.ru/8.2/managed-application/cmi" xmlns:ent="http://v8.1c.ru/8.1/data/enterprise" xmlns:lf="http://v8.1c.ru/8.2/managed-application/logform" xmlns:style="http://v8.1c.ru/8.1/data/ui/style" xmlns:sys="http://v8.1c.ru/8.1/data/ui/fonts/system" xmlns:v8="http://v8.1c.ru/8.1/data/core" xmlns:v8ui="http://v8.1c.ru/8.1/data/ui" xmlns:web="http://v8.1c.ru/8.1/data/ui/colors/web" xmlns:win="http://v8.1c.ru/8.1/data/ui/colors/windows" xmlns:xen="http://v8.1c.ru/8.3/xcf/enums" xmlns:xpr="http://v8.1c.ru/8.3/xcf/predef" xmlns:xr="http://v8.1c.ru/8.3/xcf/readable" xmlns:xs="http://www.w3.org/2001/XMLSchema" xmlns:xsi="http://www.w3.org/2001/XMLSchema-instance" version="2.1">
	<Constant uuid="0f345b25-1a12-4741-adb5-98fd39edb83b">
		<InternalInfo>
			<xr:GeneratedType name="ConstantManager.ИспользоватьФИОКонтрагентов" category="Manager">
				<xr:TypeId>75f5c807-b8ba-4a8c-91d1-d7fa5973423e</xr:TypeId>
				<xr:ValueId>34850f5c-5670-41b5-8a91-7d06c71ac49a</xr:ValueId>
			</xr:GeneratedType>
			<xr:GeneratedType name="ConstantValueManager.ИспользоватьФИОКонтрагентов" category="ValueManager">
				<xr:TypeId>80622e16-1351-4dd2-bb23-306b9dba4b77</xr:TypeId>
				<xr:ValueId>954c8f0a-8d60-476f-b0f0-571bdffae61c</xr:ValueId>
			</xr:GeneratedType>
		</InternalInfo>
		<Properties>
			<Name>ИспользоватьФИОКонтрагентов</Name>
			<Synonym>
				<v8:item>
					<v8:lang>ru</v8:lang>
					<v8:content>Использовать ФИО физических лиц</v8:content>
				</v8:item>
				<v8:item>
					<v8:lang>en</v8:lang>
					<v8:content>Use individuals name</v8:content>
				</v8:item>
				<v8:item>
					<v8:lang>az</v8:lang>
					<v8:content>İstifadə şəxslər adı</v8:content>
				</v8:item>
				<v8:item>
					<v8:lang>ar</v8:lang>
					<v8:content>اسم استخدام الأفراد</v8:content>
				</v8:item>
				<v8:item>
					<v8:lang>am</v8:lang>
					<v8:content>Օգտագործեք անհատներ անունը</v8:content>
				</v8:item>
				<v8:item>
					<v8:lang>bl</v8:lang>
					<v8:content>Выкарыстоўваць Прозвішча, імя фізічных асоб</v8:content>
				</v8:item>
				<v8:item>
					<v8:lang>bg</v8:lang>
					<v8:content>Използвайте индивиди име</v8:content>
				</v8:item>
				<v8:item>
					<v8:lang>hu</v8:lang>
					<v8:content>Felhasználási egyének neve</v8:content>
				</v8:item>
				<v8:item>
					<v8:lang>vi</v8:lang>
					<v8:content>Tên sử dụng cá nhân</v8:content>
				</v8:item>
				<v8:item>
					<v8:lang>ka</v8:lang>
					<v8:content>გამოყენება პირებს სახელი</v8:content>
				</v8:item>
				<v8:item>
					<v8:lang>zz</v8:lang>
					<v8:content>Использование личных имен</v8:content>
				</v8:item>
				<v8:item>
					<v8:lang>he</v8:lang>
					<v8:content>שם אנשים משתמשים</v8:content>
				</v8:item>
				<v8:item>
					<v8:lang>it</v8:lang>
					<v8:content>Usa nome individui</v8:content>
				</v8:item>
				<v8:item>
					<v8:lang>kk</v8:lang>
					<v8:content>Жеке тұлғалар атауын пайдаланыңыз</v8:content>
				</v8:item>
				<v8:item>
					<v8:lang>zh</v8:lang>
					<v8:content>使用个人名</v8:content>
				</v8:item>
				<v8:item>
					<v8:lang>ko</v8:lang>
					<v8:content>를 사용하여 개인의 이름</v8:content>
				</v8:item>
				<v8:item>
					<v8:lang>lt</v8:lang>
					<v8:content>Izmantojiet privātpersonas vārds</v8:content>
				</v8:item>
				<v8:item>
					<v8:lang>lv</v8:lang>
					<v8:content>Naudokite asmenys vardas</v8:content>
				</v8:item>
				<v8:item>
					<v8:lang>de</v8:lang>
					<v8:content>Verwenden Individuen Name</v8:content>
				</v8:item>
				<v8:item>
					<v8:lang>pl</v8:lang>
					<v8:content>Nazwa Użyj osoby</v8:content>
				</v8:item>
				<v8:item>
					<v8:lang>ro</v8:lang>
					<v8:content>Numele de utilizare indivizi</v8:content>
				</v8:item>
				<v8:item>
					<v8:lang>sk</v8:lang>
					<v8:content>Názov použitie jednotlivci</v8:content>
				</v8:item>
				<v8:item>
					<v8:lang>yg</v8:lang>
					<v8:content>Номи Истифодаи шахсони воқеӣ</v8:content>
				</v8:item>
				<v8:item>
					<v8:lang>th</v8:lang>
					<v8:content>ใช้ชื่อบุคคล</v8:content>
				</v8:item>
				<v8:item>
					<v8:lang>tr</v8:lang>
					<v8:content>Kullanım bireylerin isim</v8:content>
				</v8:item>
				<v8:item>
					<v8:lang>uz</v8:lang>
					<v8:content>Foydalanish shaxslar nomi</v8:content>
				</v8:item>
				<v8:item>
					<v8:lang>uk</v8:lang>
					<v8:content>Використовувати ПІБ фізичних осіб</v8:content>
				</v8:item>
				<v8:item>
					<v8:lang>fr</v8:lang>
					<v8:content>Utilisez individus nom</v8:content>
				</v8:item>
				<v8:item>
					<v8:lang>hi</v8:lang>
					<v8:content>उपयोग व्यक्तियों नाम</v8:content>
				</v8:item>
				<v8:item>
					<v8:lang>cs</v8:lang>
					<v8:content>Název použití jednotlivci</v8:content>
				</v8:item>
				<v8:item>
					<v8:lang>et</v8:lang>
					<v8:content>Kasuta üksikisikute nimi</v8:content>
				</v8:item>
				<v8:item>
					<v8:lang>ja</v8:lang>
					<v8:content>個人名を使用します</v8:content>
				</v8:item>
			</Synonym>
			<Comment/>
			<Type>
				<v8:Type>xs:boolean</v8:Type>
			</Type>
			<UseStandardCommands>true</UseStandardCommands>
			<DefaultForm/>
			<ExtendedPresentation>
				<v8:item>
					<v8:lang>ru</v8:lang>
					<v8:content>Использовать Фамилию - Имя - Отчество физических лиц</v8:content>
				</v8:item>
				<v8:item>
					<v8:lang>en</v8:lang>
					<v8:content>Use the Surname - Name - Middle individuals</v8:content>
				</v8:item>
				<v8:item>
					<v8:lang>az</v8:lang>
					<v8:content>Ad - - Soyadınız istifadə Middle şəxslər</v8:content>
				</v8:item>
				<v8:item>
					<v8:lang>ar</v8:lang>
					<v8:content>استخدام اللقب - اسم - الأفراد الأوسط</v8:content>
				</v8:item>
				<v8:item>
					<v8:lang>am</v8:lang>
					<v8:content>Օգտագործեք ազգանունը անունը - Middle անհատներին</v8:content>
				</v8:item>
				<v8:item>
					<v8:lang>bl</v8:lang>
					<v8:content>Выкарыстоўваць Прозвішча - Імя - Імя па бацьку фізічных асоб</v8:content>
				</v8:item>
				<v8:item>
					<v8:lang>bg</v8:lang>
					<v8:content>Използвайте Фамилия - име - Средните лица</v8:content>
				</v8:item>
				<v8:item>
					<v8:lang>hu</v8:lang>
					<v8:content>A következő Vezetéknév - Név - Közel az egyének</v8:content>
				</v8:item>
				<v8:item>
					<v8:lang>vi</v8:lang>
					<v8:content>Sử dụng Họ - Tên - cá nhân Trung</v8:content>
				</v8:item>
				<v8:item>
					<v8:lang>ka</v8:lang>
					<v8:content>გამოიყენეთ გვარი - სახელი - Middle პირებს</v8:content>
				</v8:item>
				<v8:item>
					<v8:lang>zz</v8:lang>
					<v8:content>Используйте Фамилия - Имя - Ближневосточный</v8:content>
				</v8:item>
				<v8:item>
					<v8:lang>he</v8:lang>
					<v8:content>השתמש משפחה - שם - אנשים התיכון</v8:content>
				</v8:item>
				<v8:item>
					<v8:lang>it</v8:lang>
					<v8:content>Utilizzare il Cognome - Nome - soggetti di mezza</v8:content>
				</v8:item>
				<v8:item>
					<v8:lang>kk</v8:lang>
					<v8:content>Аты - - жеке тұлғаларға, Тегі Таяу пайдаланыңыз</v8:content>
				</v8:item>
				<v8:item>
					<v8:lang>zh</v8:lang>
					<v8:content>使用姓 - 名 - 中东人</v8:content>
				</v8:item>
				<v8:item>
					<v8:lang>ko</v8:lang>
					<v8:content>이름 - - 성을 사용하여 중간 개인</v8:content>
				</v8:item>
				<v8:item>
					<v8:lang>lt</v8:lang>
					<v8:content>Izmantojiet uzvārds - nosaukums - Tuvo indivīdus</v8:content>
				</v8:item>
				<v8:item>
					<v8:lang>lv</v8:lang>
					<v8:content>Naudokite pavardė - name - Artimieji asmenis</v8:content>
				</v8:item>
				<v8:item>
					<v8:lang>de</v8:lang>
					<v8:content>Verwenden Sie den Familiennamen - Name - Mittel Personen</v8:content>
				</v8:item>
				<v8:item>
					<v8:lang>pl</v8:lang>
					<v8:content>Użyj Nazwisko - Imię i nazwisko - osób w średnim</v8:content>
				</v8:item>
				<v8:item>
					<v8:lang>ro</v8:lang>
					<v8:content>Utilizați Nume - Numele - persoane fizice Mediu</v8:content>
				</v8:item>
				<v8:item>
					<v8:lang>sk</v8:lang>
					<v8:content>Použite Priezvisko - Meno - stredná jednotlivcom</v8:content>
				</v8:item>
				<v8:item>
					<v8:lang>yg</v8:lang>
					<v8:content>Истифода баред Насаб - ном - шахсони воқеӣ Миёна</v8:content>
				</v8:item>
				<v8:item>
					<v8:lang>th</v8:lang>
					<v8:content>ใช้นามสกุล - ชื่อ - บุคคลกลาง</v8:content>
				</v8:item>
				<v8:item>
					<v8:lang>tr</v8:lang>
					<v8:content>Ad - - Soyadı kullanın Orta bireyler</v8:content>
				</v8:item>
				<v8:item>
					<v8:lang>uz</v8:lang>
					<v8:content>Ism - - sharifi foydalaning Yaqin shaxslar</v8:content>
				</v8:item>
				<v8:item>
					<v8:lang>uk</v8:lang>
					<v8:content>Використовувати Прізвище - Ім'я - По батькові фізичних осіб</v8:content>
				</v8:item>
				<v8:item>
					<v8:lang>fr</v8:lang>
					<v8:content>Utilisez le Nom - Nom - individus Moyen</v8:content>
				</v8:item>
				<v8:item>
					<v8:lang>hi</v8:lang>
					<v8:content>उपनाम का प्रयोग करें - नाम - मध्य व्यक्तियों</v8:content>
				</v8:item>
				<v8:item>
					<v8:lang>cs</v8:lang>
					<v8:content>Použijte Příjmení - Jméno - střední jednotlivcům</v8:content>
				</v8:item>
				<v8:item>
					<v8:lang>et</v8:lang>
					<v8:content>Kasutage Perekonnanimi - Nimi - Lähis üksikisikute</v8:content>
				</v8:item>
				<v8:item>
					<v8:lang>ja</v8:lang>
					<v8:content>名前 -   - ミドル個人姓を使用します</v8:content>
				</v8:item>
			</ExtendedPresentation>
			<Explanation>
				<v8:item>
					<v8:lang>ru</v8:lang>
					<v8:content>Использовать Фамилию - Имя - Отчество физических лиц</v8:content>
				</v8:item>
				<v8:item>
					<v8:lang>en</v8:lang>
					<v8:content>Use the Surname - Name - Middle individuals</v8:content>
				</v8:item>
				<v8:item>
					<v8:lang>az</v8:lang>
					<v8:content>Ad - - Soyadınız istifadə Middle şəxslər</v8:content>
				</v8:item>
				<v8:item>
					<v8:lang>ar</v8:lang>
					<v8:content>استخدام اللقب - اسم - الأفراد الأوسط</v8:content>
				</v8:item>
				<v8:item>
					<v8:lang>am</v8:lang>
					<v8:content>Օգտագործեք ազգանունը անունը - Middle անհատներին</v8:content>
				</v8:item>
				<v8:item>
					<v8:lang>bl</v8:lang>
					<v8:content>Выкарыстоўваць Прозвішча - Імя - Імя па бацьку фізічных асоб</v8:content>
				</v8:item>
				<v8:item>
					<v8:lang>bg</v8:lang>
					<v8:content>Използвайте Фамилия - име - Средните лица</v8:content>
				</v8:item>
				<v8:item>
					<v8:lang>hu</v8:lang>
					<v8:content>A következő Vezetéknév - Név - Közel az egyének</v8:content>
				</v8:item>
				<v8:item>
					<v8:lang>vi</v8:lang>
					<v8:content>Sử dụng Họ - Tên - cá nhân Trung</v8:content>
				</v8:item>
				<v8:item>
					<v8:lang>ka</v8:lang>
					<v8:content>გამოიყენეთ გვარი - სახელი - Middle პირებს</v8:content>
				</v8:item>
				<v8:item>
					<v8:lang>zz</v8:lang>
					<v8:content>Используйте Фамилия - Имя - Ближневосточный</v8:content>
				</v8:item>
				<v8:item>
					<v8:lang>he</v8:lang>
					<v8:content>השתמש משפחה - שם - אנשים התיכון</v8:content>
				</v8:item>
				<v8:item>
					<v8:lang>it</v8:lang>
					<v8:content>Utilizzare il Cognome - Nome - soggetti di mezza</v8:content>
				</v8:item>
				<v8:item>
					<v8:lang>kk</v8:lang>
					<v8:content>Аты - - жеке тұлғаларға, Тегі Таяу пайдаланыңыз</v8:content>
				</v8:item>
				<v8:item>
					<v8:lang>zh</v8:lang>
					<v8:content>使用姓 - 名 - 中东人</v8:content>
				</v8:item>
				<v8:item>
					<v8:lang>ko</v8:lang>
					<v8:content>이름 - - 성을 사용하여 중간 개인</v8:content>
				</v8:item>
				<v8:item>
					<v8:lang>lt</v8:lang>
					<v8:content>Izmantojiet uzvārds - nosaukums - Tuvo indivīdus</v8:content>
				</v8:item>
				<v8:item>
					<v8:lang>lv</v8:lang>
					<v8:content>Naudokite pavardė - name - Artimieji asmenis</v8:content>
				</v8:item>
				<v8:item>
					<v8:lang>de</v8:lang>
					<v8:content>Verwenden Sie den Familiennamen - Name - Mittel Personen</v8:content>
				</v8:item>
				<v8:item>
					<v8:lang>pl</v8:lang>
					<v8:content>Użyj Nazwisko - Imię i nazwisko - osób w średnim</v8:content>
				</v8:item>
				<v8:item>
					<v8:lang>ro</v8:lang>
					<v8:content>Utilizați Nume - Numele - persoane fizice Mediu</v8:content>
				</v8:item>
				<v8:item>
					<v8:lang>sk</v8:lang>
					<v8:content>Použite Priezvisko - Meno - stredná jednotlivcom</v8:content>
				</v8:item>
				<v8:item>
					<v8:lang>yg</v8:lang>
					<v8:content>Истифода баред Насаб - ном - шахсони воқеӣ Миёна</v8:content>
				</v8:item>
				<v8:item>
					<v8:lang>th</v8:lang>
					<v8:content>ใช้นามสกุล - ชื่อ - บุคคลกลาง</v8:content>
				</v8:item>
				<v8:item>
					<v8:lang>tr</v8:lang>
					<v8:content>Ad - - Soyadı kullanın Orta bireyler</v8:content>
				</v8:item>
				<v8:item>
					<v8:lang>uz</v8:lang>
					<v8:content>Ism - - sharifi foydalaning Yaqin shaxslar</v8:content>
				</v8:item>
				<v8:item>
					<v8:lang>uk</v8:lang>
					<v8:content>Використовувати Прізвище - Ім'я - По батькові фізичних осіб</v8:content>
				</v8:item>
				<v8:item>
					<v8:lang>fr</v8:lang>
					<v8:content>Utilisez le Nom - Nom - individus Moyen</v8:content>
				</v8:item>
				<v8:item>
					<v8:lang>hi</v8:lang>
					<v8:content>उपनाम का प्रयोग करें - नाम - मध्य व्यक्तियों</v8:content>
				</v8:item>
				<v8:item>
					<v8:lang>cs</v8:lang>
					<v8:content>Použijte Příjmení - Jméno - střední jednotlivcům</v8:content>
				</v8:item>
				<v8:item>
					<v8:lang>et</v8:lang>
					<v8:content>Kasutage Perekonnanimi - Nimi - Lähis üksikisikute</v8:content>
				</v8:item>
				<v8:item>
					<v8:lang>ja</v8:lang>
					<v8:content>名前 -   - ミドル個人姓を使用します</v8:content>
				</v8:item>
			</Explanation>
			<PasswordMode>false</PasswordMode>
			<Format/>
			<EditFormat/>
			<ToolTip>
				<v8:item>
					<v8:lang>ru</v8:lang>
					<v8:content>Использовать Фамилию - Имя - Отчество физических лиц</v8:content>
				</v8:item>
				<v8:item>
					<v8:lang>en</v8:lang>
					<v8:content>Use the Surname - Name - Middle individuals</v8:content>
				</v8:item>
				<v8:item>
					<v8:lang>az</v8:lang>
					<v8:content>Ad - - Soyadınız istifadə Middle şəxslər</v8:content>
				</v8:item>
				<v8:item>
					<v8:lang>ar</v8:lang>
					<v8:content>استخدام اللقب - اسم - الأفراد الأوسط</v8:content>
				</v8:item>
				<v8:item>
					<v8:lang>am</v8:lang>
					<v8:content>Օգտագործեք ազգանունը անունը - Middle անհատներին</v8:content>
				</v8:item>
				<v8:item>
					<v8:lang>bl</v8:lang>
					<v8:content>Выкарыстоўваць Прозвішча - Імя - Імя па бацьку фізічных асоб</v8:content>
				</v8:item>
				<v8:item>
					<v8:lang>bg</v8:lang>
					<v8:content>Използвайте Фамилия - име - Средните лица</v8:content>
				</v8:item>
				<v8:item>
					<v8:lang>hu</v8:lang>
					<v8:content>A következő Vezetéknév - Név - Közel az egyének</v8:content>
				</v8:item>
				<v8:item>
					<v8:lang>vi</v8:lang>
					<v8:content>Sử dụng Họ - Tên - cá nhân Trung</v8:content>
				</v8:item>
				<v8:item>
					<v8:lang>ka</v8:lang>
					<v8:content>გამოიყენეთ გვარი - სახელი - Middle პირებს</v8:content>
				</v8:item>
				<v8:item>
					<v8:lang>zz</v8:lang>
					<v8:content>Используйте Фамилия - Имя - Ближневосточный</v8:content>
				</v8:item>
				<v8:item>
					<v8:lang>he</v8:lang>
					<v8:content>השתמש משפחה - שם - אנשים התיכון</v8:content>
				</v8:item>
				<v8:item>
					<v8:lang>it</v8:lang>
					<v8:content>Utilizzare il Cognome - Nome - soggetti di mezza</v8:content>
				</v8:item>
				<v8:item>
					<v8:lang>kk</v8:lang>
					<v8:content>Аты - - жеке тұлғаларға, Тегі Таяу пайдаланыңыз</v8:content>
				</v8:item>
				<v8:item>
					<v8:lang>zh</v8:lang>
					<v8:content>使用姓 - 名 - 中东人</v8:content>
				</v8:item>
				<v8:item>
					<v8:lang>ko</v8:lang>
					<v8:content>이름 - - 성을 사용하여 중간 개인</v8:content>
				</v8:item>
				<v8:item>
					<v8:lang>lt</v8:lang>
					<v8:content>Izmantojiet uzvārds - nosaukums - Tuvo indivīdus</v8:content>
				</v8:item>
				<v8:item>
					<v8:lang>lv</v8:lang>
					<v8:content>Naudokite pavardė - name - Artimieji asmenis</v8:content>
				</v8:item>
				<v8:item>
					<v8:lang>de</v8:lang>
					<v8:content>Verwenden Sie den Familiennamen - Name - Mittel Personen</v8:content>
				</v8:item>
				<v8:item>
					<v8:lang>pl</v8:lang>
					<v8:content>Użyj Nazwisko - Imię i nazwisko - osób w średnim</v8:content>
				</v8:item>
				<v8:item>
					<v8:lang>ro</v8:lang>
					<v8:content>Utilizați Nume - Numele - persoane fizice Mediu</v8:content>
				</v8:item>
				<v8:item>
					<v8:lang>sk</v8:lang>
					<v8:content>Použite Priezvisko - Meno - stredná jednotlivcom</v8:content>
				</v8:item>
				<v8:item>
					<v8:lang>yg</v8:lang>
					<v8:content>Истифода баред Насаб - ном - шахсони воқеӣ Миёна</v8:content>
				</v8:item>
				<v8:item>
					<v8:lang>th</v8:lang>
					<v8:content>ใช้นามสกุล - ชื่อ - บุคคลกลาง</v8:content>
				</v8:item>
				<v8:item>
					<v8:lang>tr</v8:lang>
					<v8:content>Ad - - Soyadı kullanın Orta bireyler</v8:content>
				</v8:item>
				<v8:item>
					<v8:lang>uz</v8:lang>
					<v8:content>Ism - - sharifi foydalaning Yaqin shaxslar</v8:content>
				</v8:item>
				<v8:item>
					<v8:lang>uk</v8:lang>
					<v8:content>Використовувати Прізвище - Ім'я - По батькові фізичних осіб</v8:content>
				</v8:item>
				<v8:item>
					<v8:lang>fr</v8:lang>
					<v8:content>Utilisez le Nom - Nom - individus Moyen</v8:content>
				</v8:item>
				<v8:item>
					<v8:lang>hi</v8:lang>
					<v8:content>उपनाम का प्रयोग करें - नाम - मध्य व्यक्तियों</v8:content>
				</v8:item>
				<v8:item>
					<v8:lang>cs</v8:lang>
					<v8:content>Použijte Příjmení - Jméno - střední jednotlivcům</v8:content>
				</v8:item>
				<v8:item>
					<v8:lang>et</v8:lang>
					<v8:content>Kasutage Perekonnanimi - Nimi - Lähis üksikisikute</v8:content>
				</v8:item>
				<v8:item>
					<v8:lang>ja</v8:lang>
					<v8:content>名前 -   - ミドル個人姓を使用します</v8:content>
				</v8:item>
			</ToolTip>
			<MarkNegatives>false</MarkNegatives>
			<Mask/>
			<MultiLine>false</MultiLine>
			<ExtendedEdit>false</ExtendedEdit>
			<MinValue xsi:nil="true"/>
			<MaxValue xsi:nil="true"/>
			<FillChecking>DontCheck</FillChecking>
			<ChoiceFoldersAndItems>Items</ChoiceFoldersAndItems>
			<ChoiceParameterLinks/>
			<ChoiceParameters/>
			<QuickChoice>Auto</QuickChoice>
			<ChoiceForm/>
			<LinkByType/>
			<ChoiceHistoryOnInput>Auto</ChoiceHistoryOnInput>
			<DataLockControlMode>Managed</DataLockControlMode>
		</Properties>
	</Constant>
</MetaDataObject>