<?xml version="1.0" encoding="UTF-8"?>
<MetaDataObject xmlns="http://v8.1c.ru/8.3/MDClasses" xmlns:app="http://v8.1c.ru/8.2/managed-application/core" xmlns:cfg="http://v8.1c.ru/8.1/data/enterprise/current-config" xmlns:cmi="http://v8.1c.ru/8.2/managed-application/cmi" xmlns:ent="http://v8.1c.ru/8.1/data/enterprise" xmlns:lf="http://v8.1c.ru/8.2/managed-application/logform" xmlns:style="http://v8.1c.ru/8.1/data/ui/style" xmlns:sys="http://v8.1c.ru/8.1/data/ui/fonts/system" xmlns:v8="http://v8.1c.ru/8.1/data/core" xmlns:v8ui="http://v8.1c.ru/8.1/data/ui" xmlns:web="http://v8.1c.ru/8.1/data/ui/colors/web" xmlns:win="http://v8.1c.ru/8.1/data/ui/colors/windows" xmlns:xen="http://v8.1c.ru/8.3/xcf/enums" xmlns:xpr="http://v8.1c.ru/8.3/xcf/predef" xmlns:xr="http://v8.1c.ru/8.3/xcf/readable" xmlns:xs="http://www.w3.org/2001/XMLSchema" xmlns:xsi="http://www.w3.org/2001/XMLSchema-instance" version="2.1">
	<Constant uuid="0db2c432-6adc-4817-a360-267b2dd2f8b7">
		<InternalInfo>
			<xr:GeneratedType name="ConstantManager.ОсновнаяФормулаПреобразованияЦен" category="Manager">
				<xr:TypeId>27ced740-4207-4352-a66a-f9331b3bb041</xr:TypeId>
				<xr:ValueId>412c095e-3bcd-4188-9609-07af77278ae5</xr:ValueId>
			</xr:GeneratedType>
			<xr:GeneratedType name="ConstantValueManager.ОсновнаяФормулаПреобразованияЦен" category="ValueManager">
				<xr:TypeId>a3452667-064a-4985-a5a8-58a8421b91bb</xr:TypeId>
				<xr:ValueId>29dca395-32c0-4544-b1ea-b78277ec03a7</xr:ValueId>
			</xr:GeneratedType>
		</InternalInfo>
		<Properties>
			<Name>ОсновнаяФормулаПреобразованияЦен</Name>
			<Synonym>
				<v8:item>
					<v8:lang>ru</v8:lang>
					<v8:content>Формула преобразования закупочной цены в цену реализации (наценка): Цена=</v8:content>
				</v8:item>
				<v8:item>
					<v8:lang>en</v8:lang>
					<v8:content>Formula conversion in the purchase price selling price (margin): Price =</v8:content>
				</v8:item>
				<v8:item>
					<v8:lang>az</v8:lang>
					<v8:content>Alış qiyməti satış qiyməti (margin) Formula dönüşüm: Qiymət =</v8:content>
				</v8:item>
				<v8:item>
					<v8:lang>ar</v8:lang>
					<v8:content>تحويل صيغة في سعر الشراء سعر البيع (هامش): السعر =</v8:content>
				</v8:item>
				<v8:item>
					<v8:lang>am</v8:lang>
					<v8:content>Formula դարձի է գնման գինը վաճառքի գնի (մարժա): Գինը =</v8:content>
				</v8:item>
				<v8:item>
					<v8:lang>bl</v8:lang>
					<v8:content>Формула пераўтварэнні закупачнай цаны ў кошт рэалізацыі (нацэнка): Цана =</v8:content>
				</v8:item>
				<v8:item>
					<v8:lang>bg</v8:lang>
					<v8:content>Формула превръщане в продажната цена на покупната цена (марж): Цена =</v8:content>
				</v8:item>
				<v8:item>
					<v8:lang>hu</v8:lang>
					<v8:content>Formula átalakítás a vételár eladási ár (margin): Ár =</v8:content>
				</v8:item>
				<v8:item>
					<v8:lang>vi</v8:lang>
					<v8:content>Chuyển đổi công thức trong giá bán giá mua (margin): giá =</v8:content>
				</v8:item>
				<v8:item>
					<v8:lang>ka</v8:lang>
					<v8:content>ფორმულა კონვერტაციის შეძენის ფასი სარეალიზაციო ფასი (ზღვარი): ფასი =</v8:content>
				</v8:item>
				<v8:item>
					<v8:lang>zz</v8:lang>
					<v8:content>В формуле преобразования цена покупки цена продажи (маржа): Цена =</v8:content>
				</v8:item>
				<v8:item>
					<v8:lang>he</v8:lang>
					<v8:content>המרה פורמולה במחיר המכירה מחיר הרכישה (שולי): מחיר =</v8:content>
				</v8:item>
				<v8:item>
					<v8:lang>it</v8:lang>
					<v8:content>Conversione Formula nel prezzo di vendita prezzo di acquisto (margine): Prezzo =</v8:content>
				</v8:item>
				<v8:item>
					<v8:lang>kk</v8:lang>
					<v8:content>Сатып алу бағасы сату бағасынан (маржа) Формула конверсиялық: Бағасы =</v8:content>
				</v8:item>
				<v8:item>
					<v8:lang>zh</v8:lang>
					<v8:content>在购买价格销售价格（保证金）公式换算：价格=</v8:content>
				</v8:item>
				<v8:item>
					<v8:lang>ko</v8:lang>
					<v8:content>구입 가격 판매 가격 (마진)의 수식 변환 : 가격 =</v8:content>
				</v8:item>
				<v8:item>
					<v8:lang>lt</v8:lang>
					<v8:content>Formula konversijas pirkuma cena pārdošanas cenu (margin): Cena =</v8:content>
				</v8:item>
				<v8:item>
					<v8:lang>lv</v8:lang>
					<v8:content>Formulė konvertavimas į pirkimo kainą pardavimo kaina (maržos): Kaina =</v8:content>
				</v8:item>
				<v8:item>
					<v8:lang>de</v8:lang>
					<v8:content>Formel-Umwandlung im Kaufpreis Verkaufspreis (Margin): Preis =</v8:content>
				</v8:item>
				<v8:item>
					<v8:lang>pl</v8:lang>
					<v8:content>Konwersja Formuła w cenie zakupu cena sprzedaży (marża): Cena =</v8:content>
				</v8:item>
				<v8:item>
					<v8:lang>ro</v8:lang>
					<v8:content>Formula de conversie în prețul de vânzare prețul de cumpărare (marja): Preț =</v8:content>
				</v8:item>
				<v8:item>
					<v8:lang>sk</v8:lang>
					<v8:content>Konverzie vzorec v kúpnej ceny predajnej ceny (margin): Cena =</v8:content>
				</v8:item>
				<v8:item>
					<v8:lang>yg</v8:lang>
					<v8:content>Табдили формула дар нархи хариди нархи фурўши (маржа): Нарх =</v8:content>
				</v8:item>
				<v8:item>
					<v8:lang>th</v8:lang>
					<v8:content>แปลงสูตรราคาขายราคาซื้อ (ขอบ): ราคา =</v8:content>
				</v8:item>
				<v8:item>
					<v8:lang>tr</v8:lang>
					<v8:content>Satın alma fiyatı satış fiyatı (marj) Formül dönüşüm: Fiyat =</v8:content>
				</v8:item>
				<v8:item>
					<v8:lang>uz</v8:lang>
					<v8:content>Sotib olish narxi sotish narxi (margin) yilda Formula konvertatsiya: Narx =</v8:content>
				</v8:item>
				<v8:item>
					<v8:lang>uk</v8:lang>
					<v8:content>Формула перетворення закупівельної ціни в ціну реалізації (націнка): Ціна =</v8:content>
				</v8:item>
				<v8:item>
					<v8:lang>fr</v8:lang>
					<v8:content>Conversion de formule dans le prix de vente du prix d'achat (marge): Prix =</v8:content>
				</v8:item>
				<v8:item>
					<v8:lang>hi</v8:lang>
					<v8:content>खरीद मूल्य बिक्री मूल्य (मार्जिन) में फॉर्मूला रूपांतरण: मूल्य =</v8:content>
				</v8:item>
				<v8:item>
					<v8:lang>cs</v8:lang>
					<v8:content>Konverze vzorec v kupní ceny prodejní ceny (margin): Cena =</v8:content>
				</v8:item>
				<v8:item>
					<v8:lang>et</v8:lang>
					<v8:content>Vormel muundamise ostuhind müügihind (marginaal): Hind =</v8:content>
				</v8:item>
				<v8:item>
					<v8:lang>ja</v8:lang>
					<v8:content>購入価格の販売価格（マージン）における式変換：価格=</v8:content>
				</v8:item>
			</Synonym>
			<Comment/>
			<Type>
				<v8:Type>cfg:CatalogRef.ФормулыОписания</v8:Type>
			</Type>
			<UseStandardCommands>true</UseStandardCommands>
			<DefaultForm/>
			<ExtendedPresentation/>
			<Explanation/>
			<PasswordMode>false</PasswordMode>
			<Format/>
			<EditFormat/>
			<ToolTip>
				<v8:item>
					<v8:lang>ru</v8:lang>
					<v8:content>Формула преобразования закупочной цены в цену реализации (наценка)</v8:content>
				</v8:item>
				<v8:item>
					<v8:lang>en</v8:lang>
					<v8:content>Formula conversion in the purchase price selling price (margin)</v8:content>
				</v8:item>
				<v8:item>
					<v8:lang>az</v8:lang>
					<v8:content>Alış qiyməti satış qiyməti Formula dönüşüm (margin)</v8:content>
				</v8:item>
				<v8:item>
					<v8:lang>ar</v8:lang>
					<v8:content>تحويل صيغة في سعر الشراء سعر البيع (هامش)</v8:content>
				</v8:item>
				<v8:item>
					<v8:lang>am</v8:lang>
					<v8:content>Formula դարձի է գնման գինը վաճառքի գնի (մարժա)</v8:content>
				</v8:item>
				<v8:item>
					<v8:lang>bl</v8:lang>
					<v8:content>Пераўтварэнне Формула ў кошт пакупкі прадажнай цэны (рэнтабельнасць)</v8:content>
				</v8:item>
				<v8:item>
					<v8:lang>bg</v8:lang>
					<v8:content>Формула превръщане в продажната цена на покупната цена (марж)</v8:content>
				</v8:item>
				<v8:item>
					<v8:lang>hu</v8:lang>
					<v8:content>Formula átalakítás a vételár eladási ár (margin)</v8:content>
				</v8:item>
				<v8:item>
					<v8:lang>vi</v8:lang>
					<v8:content>Chuyển đổi công thức trong giá bán giá mua (margin)</v8:content>
				</v8:item>
				<v8:item>
					<v8:lang>ka</v8:lang>
					<v8:content>ფორმულა კონვერტაციის შეძენის ფასი სარეალიზაციო ფასი (ზღვარი)</v8:content>
				</v8:item>
				<v8:item>
					<v8:lang>zz</v8:lang>
					<v8:content>Наличие Цена</v8:content>
				</v8:item>
				<v8:item>
					<v8:lang>he</v8:lang>
					<v8:content>המרה פורמולה במחיר המכירה מחיר הרכישה (שולי)</v8:content>
				</v8:item>
				<v8:item>
					<v8:lang>it</v8:lang>
					<v8:content>Conversione Formula nel prezzo di vendita prezzo di acquisto (margine)</v8:content>
				</v8:item>
				<v8:item>
					<v8:lang>kk</v8:lang>
					<v8:content>Сатып алу бағасы сату бағасынан (маржа) Формула конверсиялық</v8:content>
				</v8:item>
				<v8:item>
					<v8:lang>zh</v8:lang>
					<v8:content>在购买价格的销售价格公式换算（保证金）</v8:content>
				</v8:item>
				<v8:item>
					<v8:lang>ko</v8:lang>
					<v8:content>구입 가격 판매 가격의 수식 변환 (마진)</v8:content>
				</v8:item>
				<v8:item>
					<v8:lang>lt</v8:lang>
					<v8:content>Formula konversijas pirkuma cena pārdošanas cenu (rezerve)</v8:content>
				</v8:item>
				<v8:item>
					<v8:lang>lv</v8:lang>
					<v8:content>Formulė konvertavimas į pirkimo kainą pardavimo kaina (marža)</v8:content>
				</v8:item>
				<v8:item>
					<v8:lang>de</v8:lang>
					<v8:content>Formel-Umwandlung im Kaufpreis Verkaufspreis (Marge)</v8:content>
				</v8:item>
				<v8:item>
					<v8:lang>pl</v8:lang>
					<v8:content>Konwersja Formuła w cenie zakupu cena sprzedaży (marża)</v8:content>
				</v8:item>
				<v8:item>
					<v8:lang>ro</v8:lang>
					<v8:content>Formula de conversie în prețul de vânzare prețul de cumpărare (marja)</v8:content>
				</v8:item>
				<v8:item>
					<v8:lang>sk</v8:lang>
					<v8:content>Konverzie vzorec v kúpnej ceny predajnej ceny (margin)</v8:content>
				</v8:item>
				<v8:item>
					<v8:lang>yg</v8:lang>
					<v8:content>Табдили формула дар нархи хариди нархи фурўши (маржа)</v8:content>
				</v8:item>
				<v8:item>
					<v8:lang>th</v8:lang>
					<v8:content>แปลงสูตรราคาขายราคาซื้อ (ขอบ)</v8:content>
				</v8:item>
				<v8:item>
					<v8:lang>tr</v8:lang>
					<v8:content>Satın alma fiyatı satış fiyatı Formül dönüşüm (marj)</v8:content>
				</v8:item>
				<v8:item>
					<v8:lang>uz</v8:lang>
					<v8:content>Sotib olish narxi sotish narxiga Formula konvertatsiya (margin)</v8:content>
				</v8:item>
				<v8:item>
					<v8:lang>uk</v8:lang>
					<v8:content>Формула перетворення закупівельної ціни в ціну реалізації (націнка)</v8:content>
				</v8:item>
				<v8:item>
					<v8:lang>fr</v8:lang>
					<v8:content>Conversion de formule dans le prix de vente du prix d'achat (marge)</v8:content>
				</v8:item>
				<v8:item>
					<v8:lang>hi</v8:lang>
					<v8:content>खरीद मूल्य बिक्री मूल्य में फॉर्मूला रूपांतरण (मार्जिन)</v8:content>
				</v8:item>
				<v8:item>
					<v8:lang>cs</v8:lang>
					<v8:content>Konverze vzorec v kupní ceny prodejní ceny (margin)</v8:content>
				</v8:item>
				<v8:item>
					<v8:lang>et</v8:lang>
					<v8:content>Vormel muundamise ostuhind müügihind (marginaal)</v8:content>
				</v8:item>
				<v8:item>
					<v8:lang>ja</v8:lang>
					<v8:content>購入価格の販売価格（マージン）における式変換</v8:content>
				</v8:item>
			</ToolTip>
			<MarkNegatives>false</MarkNegatives>
			<Mask/>
			<MultiLine>false</MultiLine>
			<ExtendedEdit>false</ExtendedEdit>
			<MinValue xsi:nil="true"/>
			<MaxValue xsi:nil="true"/>
			<FillChecking>DontCheck</FillChecking>
			<ChoiceFoldersAndItems>Items</ChoiceFoldersAndItems>
			<ChoiceParameterLinks/>
			<ChoiceParameters>
				<app:item name="Отбор.Родитель">
					<app:value xsi:type="xr:DesignTimeRef">Catalog.ФормулыОписания.ФормулыПреобразованияЦен</app:value>
				</app:item>
			</ChoiceParameters>
			<QuickChoice>Auto</QuickChoice>
			<ChoiceForm/>
			<LinkByType/>
			<ChoiceHistoryOnInput>Auto</ChoiceHistoryOnInput>
			<DataLockControlMode>Managed</DataLockControlMode>
		</Properties>
	</Constant>
</MetaDataObject>