<?xml version="1.0" encoding="UTF-8"?>
<MetaDataObject xmlns="http://v8.1c.ru/8.3/MDClasses" xmlns:app="http://v8.1c.ru/8.2/managed-application/core" xmlns:cfg="http://v8.1c.ru/8.1/data/enterprise/current-config" xmlns:cmi="http://v8.1c.ru/8.2/managed-application/cmi" xmlns:ent="http://v8.1c.ru/8.1/data/enterprise" xmlns:lf="http://v8.1c.ru/8.2/managed-application/logform" xmlns:style="http://v8.1c.ru/8.1/data/ui/style" xmlns:sys="http://v8.1c.ru/8.1/data/ui/fonts/system" xmlns:v8="http://v8.1c.ru/8.1/data/core" xmlns:v8ui="http://v8.1c.ru/8.1/data/ui" xmlns:web="http://v8.1c.ru/8.1/data/ui/colors/web" xmlns:win="http://v8.1c.ru/8.1/data/ui/colors/windows" xmlns:xen="http://v8.1c.ru/8.3/xcf/enums" xmlns:xpr="http://v8.1c.ru/8.3/xcf/predef" xmlns:xr="http://v8.1c.ru/8.3/xcf/readable" xmlns:xs="http://www.w3.org/2001/XMLSchema" xmlns:xsi="http://www.w3.org/2001/XMLSchema-instance" version="2.1">
	<Constant uuid="c5e96bef-9e1e-4f42-82ec-2b6adaf34c9e">
		<InternalInfo>
			<xr:GeneratedType name="ConstantManager.ФорматЭтикетки" category="Manager">
				<xr:TypeId>99c2e62b-7432-4df6-b2ee-e8383b8e3ce0</xr:TypeId>
				<xr:ValueId>f9136ac1-b6a6-41ef-b198-5be387623b69</xr:ValueId>
			</xr:GeneratedType>
			<xr:GeneratedType name="ConstantValueManager.ФорматЭтикетки" category="ValueManager">
				<xr:TypeId>a663b5fe-de43-42fc-9bff-2f5c895a4c6b</xr:TypeId>
				<xr:ValueId>f4dd19ac-afd7-4c7d-bfce-16088e931542</xr:ValueId>
			</xr:GeneratedType>
		</InternalInfo>
		<Properties>
			<Name>ФорматЭтикетки</Name>
			<Synonym>
				<v8:item>
					<v8:lang>ru</v8:lang>
					<v8:content>Формат этикетки</v8:content>
				</v8:item>
				<v8:item>
					<v8:lang>en</v8:lang>
					<v8:content>Label format</v8:content>
				</v8:item>
				<v8:item>
					<v8:lang>ro</v8:lang>
					<v8:content>Formatul etichetei</v8:content>
				</v8:item>
				<v8:item>
					<v8:lang>bl</v8:lang>
					<v8:content>Фармат этыкеткі</v8:content>
				</v8:item>
				<v8:item>
					<v8:lang>zh</v8:lang>
					<v8:content>标签格式</v8:content>
				</v8:item>
				<v8:item>
					<v8:lang>uk</v8:lang>
					<v8:content>Формат етикетки</v8:content>
				</v8:item>
				<v8:item>
					<v8:lang>BG</v8:lang>
					<v8:content>Формат на етикета</v8:content>
				</v8:item>
				<v8:item>
					<v8:lang>DE</v8:lang>
					<v8:content>Label-Format</v8:content>
				</v8:item>
				<v8:item>
					<v8:lang>PL</v8:lang>
					<v8:content>Format etykiety</v8:content>
				</v8:item>
				<v8:item>
					<v8:lang>kk</v8:lang>
					<v8:content>Заттаңбаның форматы</v8:content>
				</v8:item>
				<v8:item>
					<v8:lang>TH</v8:lang>
					<v8:content>รูปแบบฉลาก</v8:content>
				</v8:item>
			</Synonym>
			<Comment/>
			<Type>
				<v8:Type>cfg:EnumRef.ФорматыЭтикеток</v8:Type>
			</Type>
			<UseStandardCommands>true</UseStandardCommands>
			<DefaultForm/>
			<ExtendedPresentation/>
			<Explanation/>
			<PasswordMode>false</PasswordMode>
			<Format/>
			<EditFormat/>
			<ToolTip/>
			<MarkNegatives>false</MarkNegatives>
			<Mask/>
			<MultiLine>false</MultiLine>
			<ExtendedEdit>false</ExtendedEdit>
			<MinValue xsi:nil="true"/>
			<MaxValue xsi:nil="true"/>
			<FillChecking>DontCheck</FillChecking>
			<ChoiceFoldersAndItems>Items</ChoiceFoldersAndItems>
			<ChoiceParameterLinks/>
			<ChoiceParameters/>
			<QuickChoice>Auto</QuickChoice>
			<ChoiceForm/>
			<LinkByType/>
			<ChoiceHistoryOnInput>Auto</ChoiceHistoryOnInput>
			<DataLockControlMode>Managed</DataLockControlMode>
		</Properties>
	</Constant>
</MetaDataObject>